micro_poro_structure_generator/__init__.py
micro_poro_structure_generator/generate_mesh_2D_parallelogram_w_circular_inclusions.py
micro_poro_structure_generator/generate_mesh_2D_rectangle_w_circular_inclusions.py
micro_poro_structure_generator/generate_mesh_2D_rectangle_w_hexagonal_inclusions.py
micro_poro_structure_generator/generate_mesh_2D_rectangle_w_voronoi_inclusions.py
micro_poro_structure_generator/generate_mesh_2D_square_w_circular_inclusions.py
micro_poro_structure_generator/generate_mesh_3D_cube_w_spherical_inclusions.py
micro_poro_structure_generator/generate_mesh_3D_cube_w_tetrakaidecahedral_inclusions.py
micro_poro_structure_generator/generate_mesh_utils.py
micro_poro_structure_generator/generate_seeds_random.py
micro_poro_structure_generator/generate_seeds_semi_regular.py
micro_poro_structure_generator/generate_seeds_utils.py
micro_poro_structure_generator-2023.12.8.dist-info/LICENSE
micro_poro_structure_generator-2023.12.8.dist-info/METADATA
micro_poro_structure_generator-2023.12.8.dist-info/WHEEL
micro_poro_structure_generator-2023.12.8.dist-info/top_level.txt
micro_poro_structure_generator-2023.12.8.dist-info/RECORD
