Metadata-Version: 2.1
Name: micro-poro-structure-generator
Version: 2023.12.8
Home-page: https://github.com/ManoochTayebi/micro_poro_structure_generator
Author: Mahdi Manoochehrtayebi, Martin Genet
Author-email: mahdimtayebi@gmail.com
License: GPLv3
Classifier: Programming Language :: Python :: 3
Classifier: License :: OSI Approved :: GNU General Public License v3 (GPLv3)
Classifier: Operating System :: OS Independent
License-File: LICENSE
Requires-Dist: gmsh
Requires-Dist: matplotlib
Requires-Dist: numpy
Requires-Dist: scipy
